__init__.py
nested_dict_extractor.py
nested_dict_extractor-0.1.1.dist-info/LICENSE
nested_dict_extractor-0.1.1.dist-info/METADATA
nested_dict_extractor-0.1.1.dist-info/WHEEL
nested_dict_extractor-0.1.1.dist-info/top_level.txt
nested_dict_extractor-0.1.1.dist-info/RECORD
