Metadata-Version: 2.1
Name: nested-dict-extractor
Version: 0.1.1
Summary: Derive nested value from dict by providing sequence of keys
Author-email: Ivan Livadnyi <morales_lamb_0y@icloud.com>
Project-URL: Homepage, https://github.com/skatromb/nested-dict-extractor
Classifier: Programming Language :: Python :: 3
Classifier: Operating System :: OS Independent
Requires-Python: >=3.10
License-File: LICENSE
